README.md
setup.py
pulumi_bitbucket/__init__.py
pulumi_bitbucket/_inputs.py
pulumi_bitbucket/_utilities.py
pulumi_bitbucket/branch_restriction.py
pulumi_bitbucket/branching_model.py
pulumi_bitbucket/commit_file.py
pulumi_bitbucket/default_reviewers.py
pulumi_bitbucket/deploy_key.py
pulumi_bitbucket/deployment.py
pulumi_bitbucket/deployment_variable.py
pulumi_bitbucket/forked_repository.py
pulumi_bitbucket/get_current_user.py
pulumi_bitbucket/get_deployment.py
pulumi_bitbucket/get_deployments.py
pulumi_bitbucket/get_group.py
pulumi_bitbucket/get_group_members.py
pulumi_bitbucket/get_groups.py
pulumi_bitbucket/get_hook_types.py
pulumi_bitbucket/get_ip_ranges.py
pulumi_bitbucket/get_pipeline_oidc_config.py
pulumi_bitbucket/get_pipeline_oidc_config_keys.py
pulumi_bitbucket/get_user.py
pulumi_bitbucket/get_workspace.py
pulumi_bitbucket/get_workspace_members.py
pulumi_bitbucket/group.py
pulumi_bitbucket/group_membership.py
pulumi_bitbucket/hook.py
pulumi_bitbucket/outputs.py
pulumi_bitbucket/pipeline_schedule.py
pulumi_bitbucket/pipeline_ssh_key.py
pulumi_bitbucket/pipeline_ssh_known_host.py
pulumi_bitbucket/project.py
pulumi_bitbucket/project_branching_model.py
pulumi_bitbucket/project_default_reviewers.py
pulumi_bitbucket/project_group_permission.py
pulumi_bitbucket/project_user_permission.py
pulumi_bitbucket/provider.py
pulumi_bitbucket/pulumi-plugin.json
pulumi_bitbucket/py.typed
pulumi_bitbucket/repository.py
pulumi_bitbucket/repository_group_permission.py
pulumi_bitbucket/repository_user_permission.py
pulumi_bitbucket/repository_variable.py
pulumi_bitbucket/ssh_key.py
pulumi_bitbucket/workspace_hook.py
pulumi_bitbucket/workspace_variable.py
pulumi_bitbucket.egg-info/PKG-INFO
pulumi_bitbucket.egg-info/SOURCES.txt
pulumi_bitbucket.egg-info/dependency_links.txt
pulumi_bitbucket.egg-info/not-zip-safe
pulumi_bitbucket.egg-info/requires.txt
pulumi_bitbucket.egg-info/top_level.txt
pulumi_bitbucket/config/__init__.py
pulumi_bitbucket/config/vars.py