Metadata-Version: 2.1
Name: pulumi-bitbucket
Version: 0.0.11
Summary: A Pulumi package for creating and managing bitbucket cloud resources.
Home-page: https://www.pulumi.com
License: Apache-2.0
Project-URL: Repository, https://github.com/ryan-pip/pulumi-bitbucket
Keywords: pulumi bitbucket category/vcs
Platform: UNKNOWN
Requires-Python: >=3.8
